poly_crop/__init__.py
poly_crop/crop.py
poly_crop-0.4.0.dist-info/LICENSE
poly_crop-0.4.0.dist-info/METADATA
poly_crop-0.4.0.dist-info/WHEEL
poly_crop-0.4.0.dist-info/top_level.txt
poly_crop-0.4.0.dist-info/RECORD
