Metadata-Version: 2.1
Name: poly-crop
Version: 0.4.0
Summary: Python library for cropping polygons in images
Author-email: Elias Jensen <ejkonge@gmail.com>
Keywords: image,processing,crop,polygon
Classifier: Programming Language :: Python :: 3
Classifier: License :: OSI Approved :: MIT License
Classifier: Operating System :: OS Independent
Requires-Python: >=3.8
License-File: LICENSE
Requires-Dist: numpy >=1.21.0
Requires-Dist: opencv-python >=4.5.3
Requires-Dist: pillow >=8.3.1
